pak/__init__.py
pak/bit_field.py
pak/dyn_value.py
pak/test.py
pak/io/__init__.py
pak/io/connection.py
pak/io/streams.py
pak/packets/__init__.py
pak/packets/aligned_packet.py
pak/packets/packet.py
pak/packets/packet_handler.py
pak/packets/subpacket.py
pak/types/__init__.py
pak/types/array.py
pak/types/default.py
pak/types/deferring.py
pak/types/enum.py
pak/types/misc.py
pak/types/numeric.py
pak/types/optional.py
pak/types/string.py
pak/types/type.py
pak/util/__init__.py
pak/util/aio.py
pak/util/bits.py
pak/util/decorators.py
pak/util/exceptions.py
pak/util/inspection.py
pak/util/interfaces.py
pak/util/misc.py
pak-1.1.1.dist-info/licenses/LICENSE
pak-1.1.1.dist-info/METADATA
pak-1.1.1.dist-info/WHEEL
pak-1.1.1.dist-info/top_level.txt
pak-1.1.1.dist-info/RECORD
