Metadata-Version: 2.4
Name: pak
Version: 1.1.1
Summary: A general purpose packet marshaling library
Author: friedkeenan
License: Copyright 2021-2025 friedkeenan
Project-URL: Documentation, https://pak.readthedocs.io/
Project-URL: Repository, https://github.com/friedkeenan/pak
Classifier: Programming Language :: Python :: 3.9
Classifier: Programming Language :: Python :: 3.10
Classifier: Programming Language :: Python :: 3.11
Classifier: Programming Language :: Python :: 3.12
Classifier: Programming Language :: Python :: 3.13
Classifier: License :: OSI Approved :: ISC License (ISCL)
Classifier: Operating System :: OS Independent
Requires-Python: >=3.9
License-File: LICENSE
Provides-Extra: tests
Requires-Dist: pytest; extra == "tests"
Requires-Dist: pytest-cov; extra == "tests"
Requires-Dist: pytest-asyncio; extra == "tests"
Provides-Extra: docs
Requires-Dist: sphinx==7.1.2; extra == "docs"
Requires-Dist: furo; extra == "docs"
Requires-Dist: sphinx-copybutton; extra == "docs"
Dynamic: license-file
